boundfield_renderer/__init__.py
boundfield_renderer/apps.py
boundfield_renderer/registry.py
boundfield_renderer/utils.py
boundfield_renderer/registries/__init__.py
boundfield_renderer/registries/bootstrap4.py
boundfield_renderer/registries/default.py
boundfield_renderer/templates/bootstrap4/errors.html
boundfield_renderer/templates/bootstrap4/form-check.html
boundfield_renderer/templates/bootstrap4/form-group.html
boundfield_renderer/templates/bootstrap4/help_text.html
boundfield_renderer/templates/default/field.html
boundfield_renderer/templatetags/boundfield_renderer.py
django_boundfield_renderer-1.4.dist-info/LICENSE
django_boundfield_renderer-1.4.dist-info/METADATA
django_boundfield_renderer-1.4.dist-info/WHEEL
django_boundfield_renderer-1.4.dist-info/top_level.txt
django_boundfield_renderer-1.4.dist-info/RECORD
