Metadata-Version: 2.1
Name: django-boundfield-renderer
Version: 1.4
Summary: A rendering engine for Django forms using templatetags
Home-page: https://github.com/bmampaey/django-boundfield-renderer
Author: Benjamin Mampaey
Author-email: bmampaey@gmail.com
License: MIT
Download-URL: https://github.com/bmampaey/django-boundfield-renderer/tarball/master
Keywords: django,form
Platform: any
Classifier: Development Status :: 4 - Beta
Classifier: Environment :: Web Environment
Classifier: Framework :: Django
Classifier: Framework :: Django :: 2.0
Classifier: Intended Audience :: Developers
Classifier: License :: OSI Approved :: MIT License
Classifier: Operating System :: OS Independent
Classifier: Programming Language :: Python
Classifier: Programming Language :: Python :: 3.4
Classifier: Programming Language :: Python :: 3.5
Classifier: Programming Language :: Python :: 3.6
Classifier: Topic :: Software Development :: Libraries :: Python Modules
Requires-Python: >= 3.5
Requires-Dist: Django (>=2.0)
